[1,["a20C6L1KxKEYwXf9u4I5lR@22e2a","1brw/JvvpFnIvdrxpFCgMZ","232vzs/HVA/7yb6xE36z8z@2df71","232vzs/HVA/7yb6xE36z8z@229a8","232vzs/HVA/7yb6xE36z8z@22e2a","232vzs/HVA/7yb6xE36z8z@87e21","a20C6L1KxKEYwXf9u4I5lR@d60a8","a20C6L1KxKEYwXf9u4I5lR@b729e","a20C6L1KxKEYwXf9u4I5lR@a116c","a20C6L1KxKEYwXf9u4I5lR@f18e6","a20C6L1KxKEYwXf9u4I5lR@2f2dc","a20C6L1KxKEYwXf9u4I5lR@90453","a20C6L1KxKEYwXf9u4I5lR@54a69","a20C6L1KxKEYwXf9u4I5lR@d70c8","a20C6L1KxKEYwXf9u4I5lR@5160b","a20C6L1KxKEYwXf9u4I5lR@52c63","a20C6L1KxKEYwXf9u4I5lR@06e88","a20C6L1KxKEYwXf9u4I5lR@bc9ff","a20C6L1KxKEYwXf9u4I5lR@e8fa6","a20C6L1KxKEYwXf9u4I5lR@ae6f0","a20C6L1KxKEYwXf9u4I5lR@88cbf","a20C6L1KxKEYwXf9u4I5lR@e5921","a20C6L1KxKEYwXf9u4I5lR@e63b7","a20C6L1KxKEYwXf9u4I5lR@e27ae","a20C6L1KxKEYwXf9u4I5lR@510d6","a20C6L1KxKEYwXf9u4I5lR@3cf0a","a20C6L1KxKEYwXf9u4I5lR@c11a6","a20C6L1KxKEYwXf9u4I5lR@6fb36","a20C6L1KxKEYwXf9u4I5lR@2c65b","a20C6L1KxKEYwXf9u4I5lR@e7907","cfN783Z1VB95IZWLMiFR4E@da686","cfN783Z1VB95IZWLMiFR4E@c2de9","cfN783Z1VB95IZWLMiFR4E@22e2a","cfN783Z1VB95IZWLMiFR4E@87e21"],["node","_mesh","root","mainTexture","normalMap","_effectAsset","_parent","data"],[["cc.Node",["_name","_prefab","_parent","_children","_lpos","_lrot","_euler","_components"],2,4,1,12,5,5,5,9],["cc.Material",["_name","_states","_defines","_props"],0,12],["cc.Prefab",[],3],["cc.Node",["_name","_parent","_children","_prefab"],2,1,2,4],["cc.PrefabInfo",["fileId","root","asset"],2,1,1],["cc.MeshRenderer",["node","__prefab","_materials","lightmapSettings","_mesh"],3,1,4,3,4,6],["cc.CompPrefabInfo",["fileId"],2],["cc.ModelLightmapSettings",[],3],["cc.Mesh",["_native","_dataLength","_hash","_struct"],0,11]],[[4,0,1,2,2],[0,0,2,7,1,2],[5,0,1,2,3,4,1],[6,0,2],[7,1],[8,0,1,2,3,4],[1,0,1,2,3,4],[2,1],[0,0,3,1,2],[0,0,2,1,4,5,6,2],[3,0,1,2,3,2]],[[[[6,"材质",[{"rasterizerState":{},"blendState":{"targets":[{}]},"depthStencilState":{}}],[{"USE_ALBEDO_MAP":true,"USE_NORMAL_MAP":true}],[[[{"metallic":0.4000000059604645,"roughness":0.24253562092781067},"mainTexture",6,0,"normalMap",6,1]],11]]],0,0,[0,0,0],[3,4,5],[2,3,1]],[[[7],[8,"路面02",[[[9,"Cinema_4D_编辑器",-3,[0,"12IRlx/PxR/5NM16jOQQbC",-2,0],[1,0.14349998533725739,2.3705949783325195,3.7137529850006104],[3,-0.10567719670764301,0.7008995534111759,-0.1051652971083624,0.6975044131818366],[1,-1.5573896290768994e-7,90.27821260810207,-17.14822619876353]],-4],4,1],[0,"53SiLKetpdd4yQgQxhocuV",-1,0]],[1,"Default",1,[[2,-5,[3,"2dxUt1gupfjpQEJizNA2YH"],[0],[4],1]],[0,"eeab9qFE5eHp7xGYB+1atX",1,0]]],0,[0,2,1,0,2,1,0,6,1,0,-2,2,0,0,2,0,7,1,5],[0,0],[-1,1],[4,5]],[[[5,".bin",155712,3536242047,[{"primitives":[{"primitiveMode":7,"vertexBundelIndices":[0],"indexView":{"offset":107712,"length":48000,"count":12000,"stride":4}}],"vertexBundles":[{"view":{"offset":0,"length":107712,"count":2244,"stride":48},"attributes":[{"name":"a_position","format":32,"isNormalized":false},{"name":"a_normal","format":32,"isNormalized":false},{"name":"a_texCoord","format":21,"isNormalized":false},{"name":"a_tangent","format":44,"isNormalized":false}]}]},"minPosition",8,[1,-0.75,0,-24.000001907348633],"maxPosition",8,[1,0.75,0,-2.2737367036103438e-15]]]],0,0,[],[],[]],[[[5,".bin",69024,9462633,[{"primitives":[{"primitiveMode":7,"vertexBundelIndices":[0],"indexView":{"offset":50304,"length":18720,"count":4680,"stride":4}}],"vertexBundles":[{"view":{"offset":0,"length":50304,"count":1048,"stride":48},"attributes":[{"name":"a_position","format":32,"isNormalized":false},{"name":"a_normal","format":32,"isNormalized":false},{"name":"a_texCoord","format":21,"isNormalized":false},{"name":"a_tangent","format":44,"isNormalized":false}]}]},"minPosition",8,[1,0.34464791417121887,0.0021702751982957125,-0.08678575605154037],"maxPosition",8,[1,0.3702704906463623,0.14848768711090088,-0.05635031685233116]]]],0,0,[],[],[]],[[[7],[8,"骨架",[[[9,"Cinema_4D_编辑器",-3,[0,"5bpQWyCNVbmK8jzJkcLhYq",-2,0],[1,0.4320921003818512,0.7047224640846252,1.8545290231704712],[3,-0.07920035184635257,0.7359025077275806,-0.07195472162853382,0.6685785828330374],[1,1.2806273146276362e-7,95.48875510040328,-12.285449034160616]],-4],4,1],[0,"easxKGFPhfF5uDkn41Rb+z",-1,0]],[10,"骨架_obj",1,[-5,-6,-7,-8,-9,-10,-11,-12,-13,-14,-15,-16,-17,-18,-19,-20,-21,-22,-23,-24,-25,-26],[0,"43NifY4H5RVbdeWIoaRhb+",1,0]],[1,"Tube03_1",2,[[2,-27,[3,"b0Yn7aHRRWep1+r1a+rm6e"],[0],[4],1]],[0,"ca4W4IkYpRMpLK7XyioQg0",1,0]],[1,"Tube02_1",2,[[2,-28,[3,"3dXJnn3p1UxoFvw7cbJnbv"],[2],[4],3]],[0,"05dHufiHxZZ7SSFxkwTD95",1,0]],[1,"Tube01_1",2,[[2,-29,[3,"db6T8Q3fVfvZMGXg05Ydf/"],[4],[4],5]],[0,"38HZCwrfNRzp+bHJgJtHKH",1,0]],[1,"objRight_Thigh62_1",2,[[2,-30,[3,"9aIsY19uxQZZP3hztD+acw"],[6],[4],7]],[0,"59phibw49SDqW56t7BrZa+",1,0]],[1,"objRight_Thigh63_1",2,[[2,-31,[3,"f3MJ2j8Bdb7p7umvTX+1vG"],[8],[4],9]],[0,"2aHx8E605YkIF6wAK8NGUP",1,0]],[1,"objRight_Thigh61_1",2,[[2,-32,[3,"09cc8rbjBRA7FhSYtzFgDQ"],[10],[4],11]],[0,"21Zzoud+lfbL1BugtUFMky",1,0]],[1,"objAbdomen02_1",2,[[2,-33,[3,"77cke6L6ZfIIylBzYAHBWP"],[12],[4],13]],[0,"44PScUDSNV8IwKvZxM1jY2",1,0]],[1,"objAbdomen03_1",2,[[2,-34,[3,"9917GAmuxdoJU2t4yrBpHG"],[14],[4],15]],[0,"359/teE2leOYqwxFkqIUg/",1,0]],[1,"Object12_1",2,[[2,-35,[3,"33YCShgntZM505lPes1jvS"],[16],[4],17]],[0,"17Bm0SvIJek4GLzGI1EdKS",1,0]],[1,"Object13_1",2,[[2,-36,[3,"02YCarXUFdMITlwQI8N6F9"],[18],[4],19]],[0,"295pAnX09TfqwC+OUzBIYp",1,0]],[1,"objRight_Thigh70_1",2,[[2,-37,[3,"6dgP2gAlhWgL5lHh6s0cNC"],[20],[4],21]],[0,"92CaQoGE1eTotojGm2+TBQ",1,0]],[1,"objRight_Thigh69_1",2,[[2,-38,[3,"dbzVipr15Qo5OjQY7QC+UL"],[22],[4],23]],[0,"b0l73vE9xdq7vRiE0jex7F",1,0]],[1,"objRight_Thigh67_1",2,[[2,-39,[3,"b0skgbgcxW6ZzE/6UGq0J1"],[24],[4],25]],[0,"aeGGiaQ4JSlbV9I/h/1xgH",1,0]],[1,"objRight_Thigh68_1",2,[[2,-40,[3,"d8PGtCzcBSQ4BpaYwBnMUQ"],[26],[4],27]],[0,"bcCntMBVhbc4Cf7oamm48e",1,0]],[1,"objRight_Thigh71_1",2,[[2,-41,[3,"f2AOtppl9fFL+AzsgugaAA"],[28],[4],29]],[0,"3a5NQ53RFTTYB2m61ANeul",1,0]],[1,"objRight_Thigh72_1",2,[[2,-42,[3,"7eAlCkvPBSkqOBL1HVhMqP"],[30],[4],31]],[0,"539a0NHR9cVoPcj8his3pi",1,0]],[1,"skull01_1",2,[[2,-43,[3,"fa7bkKRUlckbGAQGUeU6Ix"],[32],[4],33]],[0,"07vphsMOVdsIhOsAGuVqsv",1,0]],[1,"L_Knee01_1",2,[[2,-44,[3,"79hoh1W01cn5A7g58bcNFg"],[34],[4],35]],[0,"aa83zGtwtTPLxa3DYt7x/p",1,0]],[1,"Object15_1",2,[[2,-45,[3,"5dzQ4E/olZpos3f0ZHKtB3"],[36],[4],37]],[0,"d82V3Ms6VdFq6qhTVkiti8",1,0]],[1,"objRight_Thigh73_1",2,[[2,-46,[3,"46/PHXHf9fVJkMjK+a+hvX"],[38],[4],39]],[0,"adNXd4AFhZirximBjaoS1d",1,0]],[1,"objRight_Thigh74_1",2,[[2,-47,[3,"cbi6Lyyr1VBqY+I7dgIwYh"],[40],[4],41]],[0,"02rpn7NLVdVpkHJqIak0+2",1,0]],[1,"objRight_Thigh75_1",2,[[2,-48,[3,"14CwE68AJfW7IhccdUqZEe"],[42],[4],43]],[0,"6cd8dG3ERX6JkMSXxw/sQs",1,0]]],0,[0,2,1,0,2,1,0,6,1,0,-2,2,0,-1,3,0,-2,4,0,-3,5,0,-4,6,0,-5,7,0,-6,8,0,-7,9,0,-8,10,0,-9,11,0,-10,12,0,-11,13,0,-12,14,0,-13,15,0,-14,16,0,-15,17,0,-16,18,0,-17,19,0,-18,20,0,-19,21,0,-20,22,0,-21,23,0,-22,24,0,0,3,0,0,4,0,0,5,0,0,6,0,0,7,0,0,8,0,0,9,0,0,10,0,0,11,0,0,12,0,0,13,0,0,14,0,0,15,0,0,16,0,0,17,0,0,18,0,0,19,0,0,20,0,0,21,0,0,22,0,0,23,0,0,24,0,7,1,48],[0,0,0,0,0,0,0,0,0,0,0,0,0,0,0,0,0,0,0,0,0,0,0,0,0,0,0,0,0,0,0,0,0,0,0,0,0,0,0,0,0,0,0,0],[-1,1,-1,1,-1,1,-1,1,-1,1,-1,1,-1,1,-1,1,-1,1,-1,1,-1,1,-1,1,-1,1,-1,1,-1,1,-1,1,-1,1,-1,1,-1,1,-1,1,-1,1,-1,1],[0,6,0,7,0,8,0,9,0,10,0,11,0,12,0,13,0,14,0,15,0,16,0,17,0,18,0,19,0,20,0,21,0,22,0,23,0,24,0,25,0,26,0,27]],[[[6,"材质",[{"rasterizerState":{},"blendState":{"targets":[{}]},"depthStencilState":{}}],[{"USE_ALBEDO_MAP":true,"USE_NORMAL_MAP":true}],[[[{"metallic":0.4000000059604645,"roughness":0.24253562092781067},"mainTexture",6,0,"normalMap",6,1]],11]]],0,0,[0,0,0],[3,4,5],[28,29,1]],[[[5,".bin",94104,1054038769,[{"primitives":[{"primitiveMode":7,"vertexBundelIndices":[0],"indexView":{"offset":70800,"length":23304,"count":5826,"stride":4}}],"vertexBundles":[{"view":{"offset":0,"length":70800,"count":1475,"stride":48},"attributes":[{"name":"a_position","format":32,"isNormalized":false},{"name":"a_normal","format":32,"isNormalized":false},{"name":"a_texCoord","format":21,"isNormalized":false},{"name":"a_tangent","format":44,"isNormalized":false}]}]},"minPosition",8,[1,-0.2855915129184723,-0.004696084186434746,0.004974013194441795],"maxPosition",8,[1,-0.23829862475395203,0.42730703949928284,0.08818867057561874]]]],0,0,[],[],[]],[[[5,".bin",29304,1385276219,[{"primitives":[{"primitiveMode":7,"vertexBundelIndices":[0],"indexView":{"offset":23184,"length":6120,"count":1530,"stride":4}}],"vertexBundles":[{"view":{"offset":0,"length":23184,"count":483,"stride":48},"attributes":[{"name":"a_position","format":32,"isNormalized":false},{"name":"a_normal","format":32,"isNormalized":false},{"name":"a_texCoord","format":21,"isNormalized":false},{"name":"a_tangent","format":44,"isNormalized":false}]}]},"minPosition",8,[1,0.35557225346565247,-0.024271802976727486,0.03160242363810539],"maxPosition",8,[1,0.5093101859092712,0.02893485501408577,0.16408076882362366]]]],0,0,[],[],[]],[[[5,".bin",42264,2011099586,[{"primitives":[{"primitiveMode":7,"vertexBundelIndices":[0],"indexView":{"offset":33792,"length":8472,"count":2118,"stride":4}}],"vertexBundles":[{"view":{"offset":0,"length":33792,"count":704,"stride":48},"attributes":[{"name":"a_position","format":32,"isNormalized":false},{"name":"a_normal","format":32,"isNormalized":false},{"name":"a_texCoord","format":21,"isNormalized":false},{"name":"a_tangent","format":44,"isNormalized":false}]}]},"minPosition",8,[1,0.438471257686615,-0.016453761607408524,-0.029116827994585037],"maxPosition",8,[1,0.5699315667152405,0.09575334191322327,0.08339272439479828]]]],0,0,[],[],[]],[[[5,".bin",4404,3929987756,[{"primitives":[{"primitiveMode":7,"vertexBundelIndices":[0],"indexView":{"offset":3744,"length":660,"count":165,"stride":4}}],"vertexBundles":[{"view":{"offset":0,"length":3744,"count":78,"stride":48},"attributes":[{"name":"a_position","format":32,"isNormalized":false},{"name":"a_normal","format":32,"isNormalized":false},{"name":"a_texCoord","format":21,"isNormalized":false},{"name":"a_tangent","format":44,"isNormalized":false}]}]},"minPosition",8,[1,0.6850584149360657,-0.009328624233603477,0.016748446971178055],"maxPosition",8,[1,0.7362030744552612,0.03030840866267681,0.05308757722377777]]]],0,0,[],[],[]],[[[5,".bin",9456,2047515776,[{"primitives":[{"primitiveMode":7,"vertexBundelIndices":[0],"indexView":{"offset":7056,"length":2400,"count":600,"stride":4}}],"vertexBundles":[{"view":{"offset":0,"length":7056,"count":147,"stride":48},"attributes":[{"name":"a_position","format":32,"isNormalized":false},{"name":"a_normal","format":32,"isNormalized":false},{"name":"a_texCoord","format":21,"isNormalized":false},{"name":"a_tangent","format":44,"isNormalized":false}]}]},"minPosition",8,[1,0.6667194366455078,-0.0006487504579126835,0.019168991595506668],"maxPosition",8,[1,0.715924084186554,0.11945371329784393,0.0968412309885025]]]],0,0,[],[],[]],[[[5,".bin",129852,1879816858,[{"primitives":[{"primitiveMode":7,"vertexBundelIndices":[0],"indexView":{"offset":98256,"length":31596,"count":7899,"stride":4}}],"vertexBundles":[{"view":{"offset":0,"length":98256,"count":2047,"stride":48},"attributes":[{"name":"a_position","format":32,"isNormalized":false},{"name":"a_normal","format":32,"isNormalized":false},{"name":"a_texCoord","format":21,"isNormalized":false},{"name":"a_tangent","format":44,"isNormalized":false}]}]},"minPosition",8,[1,0.609537661075592,-0.009328624233603477,-0.1194780096411705],"maxPosition",8,[1,0.6996057629585266,0.34937340021133423,0.07740426808595657]]]],0,0,[],[],[]],[[[5,".bin",15768,2616885101,[{"primitives":[{"primitiveMode":7,"vertexBundelIndices":[0],"indexView":{"offset":12432,"length":3336,"count":834,"stride":4}}],"vertexBundles":[{"view":{"offset":0,"length":12432,"count":259,"stride":48},"attributes":[{"name":"a_position","format":32,"isNormalized":false},{"name":"a_normal","format":32,"isNormalized":false},{"name":"a_texCoord","format":21,"isNormalized":false},{"name":"a_tangent","format":44,"isNormalized":false}]}]},"minPosition",8,[1,0.28250226378440857,-0.0046211001463234425,0.08888125419616699],"maxPosition",8,[1,0.37605205178260803,0.025976188480854034,0.17394252121448517]]]],0,0,[],[],[]],[[[5,".bin",69780,3510027512,[{"primitives":[{"primitiveMode":7,"vertexBundelIndices":[0],"indexView":{"offset":51072,"length":18708,"count":4677,"stride":4}}],"vertexBundles":[{"view":{"offset":0,"length":51072,"count":1064,"stride":48},"attributes":[{"name":"a_position","format":32,"isNormalized":false},{"name":"a_normal","format":32,"isNormalized":false},{"name":"a_texCoord","format":21,"isNormalized":false},{"name":"a_tangent","format":44,"isNormalized":false}]}]},"minPosition",8,[1,0.3265018165111542,-0.0027320217341184616,-0.11439108103513718],"maxPosition",8,[1,0.35697636008262634,0.30906233191490173,0.012422232888638973]]]],0,0,[],[],[]],[[[5,".bin",69264,3545705047,[{"primitives":[{"primitiveMode":7,"vertexBundelIndices":[0],"indexView":{"offset":50544,"length":18720,"count":4680,"stride":4}}],"vertexBundles":[{"view":{"offset":0,"length":50544,"count":1053,"stride":48},"attributes":[{"name":"a_position","format":32,"isNormalized":false},{"name":"a_normal","format":32,"isNormalized":false},{"name":"a_texCoord","format":21,"isNormalized":false},{"name":"a_tangent","format":44,"isNormalized":false}]}]},"minPosition",8,[1,-0.3609479069709778,-0.004696310963481665,-0.06647580862045288],"maxPosition",8,[1,-0.31964027881622314,0.3926851749420166,-0.017409613355994225]]]],0,0,[],[],[]],[[[5,".bin",15936,2330733672,[{"primitives":[{"primitiveMode":7,"vertexBundelIndices":[0],"indexView":{"offset":12480,"length":3456,"count":864,"stride":4}}],"vertexBundles":[{"view":{"offset":0,"length":12480,"count":260,"stride":48},"attributes":[{"name":"a_position","format":32,"isNormalized":false},{"name":"a_normal","format":32,"isNormalized":false},{"name":"a_texCoord","format":21,"isNormalized":false},{"name":"a_tangent","format":44,"isNormalized":false}]}]},"minPosition",8,[1,-0.030287230387330055,-2.000000033724767e-16,-0.0984453409910202],"maxPosition",8,[1,0.030287230387330055,0.4140884280204773,-0.03971041366457939]]]],0,0,[],[],[]],[[[5,".bin",67248,2171247762,[{"primitives":[{"primitiveMode":7,"vertexBundelIndices":[0],"indexView":{"offset":48528,"length":18720,"count":4680,"stride":4}}],"vertexBundles":[{"view":{"offset":0,"length":48528,"count":1011,"stride":48},"attributes":[{"name":"a_position","format":32,"isNormalized":false},{"name":"a_normal","format":32,"isNormalized":false},{"name":"a_texCoord","format":21,"isNormalized":false},{"name":"a_tangent","format":44,"isNormalized":false}]}]},"minPosition",8,[1,0.3570796251296997,0.0025395068805664778,-0.05014217272400856],"maxPosition",8,[1,0.38521304726600647,0.2731848955154419,0.03834666311740875]]]],0,0,[],[],[]],[[[5,".bin",12864,3854145594,[{"primitives":[{"primitiveMode":7,"vertexBundelIndices":[0],"indexView":{"offset":10272,"length":2592,"count":648,"stride":4}}],"vertexBundles":[{"view":{"offset":0,"length":10272,"count":214,"stride":48},"attributes":[{"name":"a_position","format":32,"isNormalized":false},{"name":"a_normal","format":32,"isNormalized":false},{"name":"a_texCoord","format":21,"isNormalized":false},{"name":"a_tangent","format":44,"isNormalized":false}]}]},"minPosition",8,[1,-0.029821373522281647,-1.0000000168623835e-16,-0.07334206998348236],"maxPosition",8,[1,0.029821373522281647,0.27392613887786865,0.023282740265130997]]]],0,0,[],[],[]],[[[5,".bin",68064,457871715,[{"primitives":[{"primitiveMode":7,"vertexBundelIndices":[0],"indexView":{"offset":49344,"length":18720,"count":4680,"stride":4}}],"vertexBundles":[{"view":{"offset":0,"length":49344,"count":1028,"stride":48},"attributes":[{"name":"a_position","format":32,"isNormalized":false},{"name":"a_normal","format":32,"isNormalized":false},{"name":"a_texCoord","format":21,"isNormalized":false},{"name":"a_tangent","format":44,"isNormalized":false}]}]},"minPosition",8,[1,0.2328864485025406,0.0032843879889696836,-0.10715466737747192],"maxPosition",8,[1,0.25889089703559875,0.21371833980083466,-0.06563305109739304]]]],0,0,[],[],[]],[[[5,".bin",17280,1903548338,[{"primitives":[{"primitiveMode":7,"vertexBundelIndices":[0],"indexView":{"offset":13632,"length":3648,"count":912,"stride":4}}],"vertexBundles":[{"view":{"offset":0,"length":13632,"count":284,"stride":48},"attributes":[{"name":"a_position","format":32,"isNormalized":false},{"name":"a_normal","format":32,"isNormalized":false},{"name":"a_texCoord","format":21,"isNormalized":false},{"name":"a_tangent","format":44,"isNormalized":false}]}]},"minPosition",8,[1,0.323792427778244,-0.02317173033952713,0.03773495554924011],"maxPosition",8,[1,0.547058641910553,0.05475880578160286,0.11223792284727097]]]],0,0,[],[],[]],[[[5,".bin",20136,1850380181,[{"primitives":[{"primitiveMode":7,"vertexBundelIndices":[0],"indexView":{"offset":15696,"length":4440,"count":1110,"stride":4}}],"vertexBundles":[{"view":{"offset":0,"length":15696,"count":327,"stride":48},"attributes":[{"name":"a_position","format":32,"isNormalized":false},{"name":"a_normal","format":32,"isNormalized":false},{"name":"a_texCoord","format":21,"isNormalized":false},{"name":"a_tangent","format":44,"isNormalized":false}]}]},"minPosition",8,[1,-0.053525034338235855,-2.000000033724767e-16,0.04105621948838234],"maxPosition",8,[1,0.053525034338235855,0.44104695320129395,0.14715887606143951]]]],0,0,[],[],[]],[[[5,".bin",112236,3043050940,[{"primitives":[{"primitiveMode":7,"vertexBundelIndices":[0],"indexView":{"offset":85248,"length":26988,"count":6747,"stride":4}}],"vertexBundles":[{"view":{"offset":0,"length":85248,"count":1776,"stride":48},"attributes":[{"name":"a_position","format":32,"isNormalized":false},{"name":"a_normal","format":32,"isNormalized":false},{"name":"a_texCoord","format":21,"isNormalized":false},{"name":"a_tangent","format":44,"isNormalized":false}]}]},"minPosition",8,[1,0.6387713551521301,-0.009328624233603477,-0.16185152530670166],"maxPosition",8,[1,0.7412757277488708,0.3471536636352539,0.018079007044434547]]]],0,0,[],[],[]],[[[5,".bin",24768,3087729669,[{"primitives":[{"primitiveMode":7,"vertexBundelIndices":[0],"indexView":{"offset":19920,"length":4848,"count":1212,"stride":4}}],"vertexBundles":[{"view":{"offset":0,"length":19920,"count":415,"stride":48},"attributes":[{"name":"a_position","format":32,"isNormalized":false},{"name":"a_normal","format":32,"isNormalized":false},{"name":"a_texCoord","format":21,"isNormalized":false},{"name":"a_tangent","format":44,"isNormalized":false}]}]},"minPosition",8,[1,0.1719493865966797,-0.022010285407304764,-0.13053157925605774],"maxPosition",8,[1,0.5084959268569946,0.03642759099602699,-0.013604486361145973]]]],0,0,[],[],[]],[[[5,".bin",70644,3359522456,[{"primitives":[{"primitiveMode":7,"vertexBundelIndices":[0],"indexView":{"offset":51936,"length":18708,"count":4677,"stride":4}}],"vertexBundles":[{"view":{"offset":0,"length":51936,"count":1082,"stride":48},"attributes":[{"name":"a_position","format":32,"isNormalized":false},{"name":"a_normal","format":32,"isNormalized":false},{"name":"a_texCoord","format":21,"isNormalized":false},{"name":"a_tangent","format":44,"isNormalized":false}]}]},"minPosition",8,[1,0.24229814112186432,-0.0027322224341332912,-0.1386639028787613],"maxPosition",8,[1,0.3360298275947571,0.3275034725666046,0.0699932873249054]]]],0,0,[],[],[]],[[[5,".bin",51456,1113361176,[{"primitives":[{"primitiveMode":7,"vertexBundelIndices":[0],"indexView":{"offset":35856,"length":15600,"count":3900,"stride":4}}],"vertexBundles":[{"view":{"offset":0,"length":35856,"count":747,"stride":48},"attributes":[{"name":"a_position","format":32,"isNormalized":false},{"name":"a_normal","format":32,"isNormalized":false},{"name":"a_texCoord","format":21,"isNormalized":false},{"name":"a_tangent","format":44,"isNormalized":false}]}]},"minPosition",8,[1,0.16809360682964325,-0.003159817075356841,-0.0803760439157486],"maxPosition",8,[1,0.32800400257110596,0.11905625462532043,0.09144261479377747]]]],0,0,[],[],[]],[[[5,".bin",48732,1240766356,[{"primitives":[{"primitiveMode":7,"vertexBundelIndices":[0],"indexView":{"offset":36432,"length":12300,"count":3075,"stride":4}}],"vertexBundles":[{"view":{"offset":0,"length":36432,"count":759,"stride":48},"attributes":[{"name":"a_position","format":32,"isNormalized":false},{"name":"a_normal","format":32,"isNormalized":false},{"name":"a_texCoord","format":21,"isNormalized":false},{"name":"a_tangent","format":44,"isNormalized":false}]}]},"minPosition",8,[1,0.37898963689804077,0.000838153122458607,-0.029232550412416458],"maxPosition",8,[1,0.39862892031669617,0.0930754691362381,-0.0020949281752109528]]]],0,0,[],[],[]],[[[5,".bin",70512,2835519953,[{"primitives":[{"primitiveMode":7,"vertexBundelIndices":[0],"indexView":{"offset":51792,"length":18720,"count":4680,"stride":4}}],"vertexBundles":[{"view":{"offset":0,"length":51792,"count":1079,"stride":48},"attributes":[{"name":"a_position","format":32,"isNormalized":false},{"name":"a_normal","format":32,"isNormalized":false},{"name":"a_texCoord","format":21,"isNormalized":false},{"name":"a_tangent","format":44,"isNormalized":false}]}]},"minPosition",8,[1,-0.31265828013420105,-0.004696084186434746,-0.028909852728247643],"maxPosition",8,[1,-0.2713506519794464,0.3926851749420166,0.019632592797279358]]]],0,0,[],[],[]],[[[6,"材质",[{"rasterizerState":{},"blendState":{"targets":[{}]},"depthStencilState":{}}],[{"USE_ALBEDO_MAP":true,"USE_NORMAL_MAP":true}],[[[{"metallic":0.4000000059604645,"roughness":0.24253562092781067},"mainTexture",6,0,"normalMap",6,1]],11]]],0,0,[0,0,0],[3,4,5],[30,31,1]],[[[7],[8,"沙漠02",[[[9,"Cinema_4D_编辑器",-3,[0,"abAZ/+wDVb7Yi19hIh/I9T",-2,0],[1,0.0930936336517334,11.162559509277344,16.19439697265625],[3,-0.15099861960791608,0.6890492321942787,-0.15172837416263657,0.6923792840365328],[1,4.521587567236386e-7,89.72376785932902,-24.72088019164088]],-4],4,1],[0,"8106eEhddQNpCpCdHneeMf",-1,0]],[1,"Default",1,[[2,-5,[3,"78hRweXyhaw6z4TfqmctH/"],[0],[4],1]],[0,"fdlQbQyhlZupdzhFJXN9bE",1,0]]],0,[0,2,1,0,2,1,0,6,1,0,-2,2,0,0,2,0,7,1,5],[0,0],[-1,1],[32,33]],[[[5,".bin",638604,318287221,[{"primitives":[{"primitiveMode":7,"vertexBundelIndices":[0],"indexView":{"offset":446640,"length":191964,"count":47991,"stride":4}}],"vertexBundles":[{"view":{"offset":0,"length":446640,"count":9305,"stride":48},"attributes":[{"name":"a_position","format":32,"isNormalized":false},{"name":"a_normal","format":32,"isNormalized":false},{"name":"a_texCoord","format":21,"isNormalized":false},{"name":"a_tangent","format":44,"isNormalized":false}]}]},"minPosition",8,[1,-5.8719329833984375,-0.15545959770679474,-21.379840850830078],"maxPosition",8,[1,5.8719329833984375,0.17955920100212097,2.6201610565185547]]]],0,0,[],[],[]]]]
